syk4y/__init__.py
syk4y/compress.py
syk4y/printer.py
syk4y/rclone.py
syk4y-1.7.4.dist-info/METADATA
syk4y-1.7.4.dist-info/WHEEL
syk4y-1.7.4.dist-info/licenses/LICENSE
syk4y-1.7.4.dist-info/RECORD
